meshcat/__init__.py
meshcat/animation.py
meshcat/commands.py
meshcat/geometry.py
meshcat/path.py
meshcat/transformations.py
meshcat/visualizer.py
meshcat/examples/box.py
meshcat/examples/lines.ipynb
meshcat/examples/points.py
meshcat/servers/__init__.py
meshcat/servers/tree.py
meshcat/servers/zmqserver.py
meshcat/tests/__init__.py
meshcat/tests/dummy_websocket_client.py
meshcat/tests/test_drawing.py
meshcat/tests/test_ports.py
meshcat/tests/test_start_server.py
meshcat/tests/data/mesh_0_convex_piece_0.dae
meshcat/tests/data/mesh_0_convex_piece_0.obj
meshcat/tests/data/mesh_0_convex_piece_0.stl_ascii
meshcat/tests/data/mesh_0_convex_piece_0.stl_binary
meshcat/tests/data/slotted_disk.stl
meshcat/tests/data/ur10_base.dae
meshcat/viewer/.git
meshcat/viewer/.gitignore
meshcat/viewer/.gitmodules
meshcat/viewer/LICENSE
meshcat/viewer/Readme.md
meshcat/viewer/package.json
meshcat/viewer/webpack.config.js
meshcat/viewer/yarn.lock
meshcat/viewer/data/HeadTextureMultisense.png
meshcat/viewer/data/head_multisense.obj
meshcat/viewer/dist/.gitignore
meshcat/viewer/dist/animation-dev.html
meshcat/viewer/dist/camera-dev.html
meshcat/viewer/dist/index.html
meshcat/viewer/dist/main.js
meshcat/viewer/dist/main.min.js
meshcat/viewer/dist/main.min.js.LICENSE.txt
meshcat/viewer/dist/main.min.js.THIRD_PARTY_LICENSES.json
meshcat/viewer/src/ColladaLoader.js
meshcat/viewer/src/LoaderSupport.js
meshcat/viewer/src/OBJLoader2.js
meshcat/viewer/src/OrbitControls.js
meshcat/viewer/src/STLLoader.js
meshcat/viewer/src/index.js
meshcat/viewer/test/animation.html
meshcat/viewer/test/animation2.html
meshcat/viewer/test/background.html
meshcat/viewer/test/camera_control.html
meshcat/viewer/test/controls.html
meshcat/viewer/test/empty_scene.html
meshcat/viewer/test/main.js
meshcat/viewer/test/main.min.js
meshcat/viewer/test/meshfile_geometry_dae.html
meshcat/viewer/test/meshfile_geometry_obj.html
meshcat/viewer/test/meshfile_geometry_stl.html
meshcat/viewer/test/meshfile_object_dae.html
meshcat-0.3.2.dist-info/LICENSE.txt
meshcat-0.3.2.dist-info/METADATA
meshcat-0.3.2.dist-info/WHEEL
meshcat-0.3.2.dist-info/entry_points.txt
meshcat-0.3.2.dist-info/top_level.txt
meshcat-0.3.2.dist-info/RECORD
